[{"date_processed": "2024-02-11T13:33:54.839153", "total": 287, "saved": 226, "not_saved": 61, "percent_saved": 78.7, "percent_not_saved": 21.3, "d1": {"saved": 62, "not_saved": 14, "total": 76, "percent_saved": 81.6, "percent_not_saved": 18.4}, "d2": {"saved": 48, "not_saved": 14, "total": 62, "percent_saved": 77.4, "percent_not_saved": 22.6}, "d3": {"saved": 116, "not_saved": 32, "total": 148, "percent_saved": 78.4, "percent_not_saved": 21.6}}, {"date_processed": "2024-02-11T14:27:17.364606", "total": 286, "saved": 223, "not_saved": 63, "percent_saved": 78, "percent_not_saved": 22, "d1": {"saved": 61, "not_saved": 15, "total": 76, "percent_saved": 80.3, "percent_not_saved": 19.7}, "d2": {"saved": 48, "not_saved": 14, "total": 62, "percent_saved": 77.4, "percent_not_saved": 22.6}, "d3": {"saved": 114, "not_saved": 34, "total": 148, "percent_saved": 77, "percent_not_saved": 23}}, {"date_processed": "2024-02-11T14:48:33.667903", "total": 286, "saved": 224, "not_saved": 62, "percent_saved": 78.3, "percent_not_saved": 21.7, "d1": {"saved": 62, "not_saved": 14, "total": 76, "percent_saved": 81.6, "percent_not_saved": 18.4}, "d2": {"saved": 48, "not_saved": 14, "total": 62, "percent_saved": 77.4, "percent_not_saved": 22.6}, "d3": {"saved": 114, "not_saved": 34, "total": 148, "percent_saved": 77.0, "percent_not_saved": 23.0}}, {"date_processed": "2024-02-11T14:48:53.183641", "total": 286, "saved": 223, "not_saved": 63, "percent_saved": 78.0, "percent_not_saved": 22.0, "d1": {"saved": 61, "not_saved": 15, "total": 76, "percent_saved": 80.3, "percent_not_saved": 19.7}, "d2": {"saved": 48, "not_saved": 14, "total": 62, "percent_saved": 77.4, "percent_not_saved": 22.6}, "d3": {"saved": 114, "not_saved": 34, "total": 148, "percent_saved": 77.0, "percent_not_saved": 23.0}}, {"date_processed": "2024-02-11T16:32:07.604915", "total": 286, "saved": 224, "not_saved": 62, "percent_saved": 78.3, "percent_not_saved": 21.7, "d1": {"saved": 62, "not_saved": 14, "total": 76, "percent_saved": 81.6, "percent_not_saved": 18.4}, "d2": {"saved": 48, "not_saved": 14, "total": 62, "percent_saved": 77.4, "percent_not_saved": 22.6}, "d3": {"saved": 114, "not_saved": 34, "total": 148, "percent_saved": 77.0, "percent_not_saved": 23.0}}, {"date_processed": "2024-02-11T16:58:00.658775", "total": 286, "saved": 225, "not_saved": 61, "percent_saved": 78.7, "percent_not_saved": 21.3, "d1": {"saved": 62, "not_saved": 14, "total": 76, "percent_saved": 81.6, "percent_not_saved": 18.4}, "d2": {"saved": 49, "not_saved": 13, "total": 62, "percent_saved": 79.0, "percent_not_saved": 21.0}, "d3": {"saved": 114, "not_saved": 34, "total": 148, "percent_saved": 77.0, "percent_not_saved": 23.0}}, {"date_processed": "2024-02-11T17:02:54.773371", "total": 286, "saved": 226, "not_saved": 60, "percent_saved": 79.0, "percent_not_saved": 21.0, "d1": {"saved": 62, "not_saved": 14, "total": 76, "percent_saved": 81.6, "percent_not_saved": 18.4}, "d2": {"saved": 50, "not_saved": 12, "total": 62, "percent_saved": 80.6, "percent_not_saved": 19.4}, "d3": {"saved": 114, "not_saved": 34, "total": 148, "percent_saved": 77.0, "percent_not_saved": 23.0}}, {"date_processed": "2024-02-11T17:10:47.879333", "total": 286, "saved": 226, "not_saved": 60, "percent_saved": 79.0, "percent_not_saved": 21.0, "d1": {"saved": 62, "not_saved": 14, "total": 76, "percent_saved": 81.6, "percent_not_saved": 18.4}, "d2": {"saved": 50, "not_saved": 12, "total": 62, "percent_saved": 80.6, "percent_not_saved": 19.4}, "d3": {"saved": 114, "not_saved": 34, "total": 148, "percent_saved": 77.0, "percent_not_saved": 23.0}}, {"date_processed": "2024-02-11T18:03:18.249454", "total": 286, "saved": 227, "not_saved": 59, "percent_saved": 79.4, "percent_not_saved": 20.6, "d1": {"saved": 62, "not_saved": 14, "total": 76, "percent_saved": 81.6, "percent_not_saved": 18.4}, "d2": {"saved": 50, "not_saved": 12, "total": 62, "percent_saved": 80.6, "percent_not_saved": 19.4}, "d3": {"saved": 115, "not_saved": 33, "total": 148, "percent_saved": 77.7, "percent_not_saved": 22.3}}, {"date_processed": "2024-02-11T18:19:11.373369", "total": 286, "saved": 241, "not_saved": 45, "percent_saved": 84.3, "percent_not_saved": 15.7, "d1": {"saved": 66, "not_saved": 10, "total": 76, "percent_saved": 86.8, "percent_not_saved": 13.2}, "d2": {"saved": 51, "not_saved": 11, "total": 62, "percent_saved": 82.3, "percent_not_saved": 17.7}, "d3": {"saved": 124, "not_saved": 24, "total": 148, "percent_saved": 83.8, "percent_not_saved": 16.2}}, {"date_processed": "2024-02-11T19:02:04.956092", "total": 286, "saved": 241, "not_saved": 45, "percent_saved": 84.3, "percent_not_saved": 15.7, "d1": {"saved": 66, "not_saved": 10, "total": 76, "percent_saved": 86.8, "percent_not_saved": 13.2}, "d2": {"saved": 51, "not_saved": 11, "total": 62, "percent_saved": 82.3, "percent_not_saved": 17.7}, "d3": {"saved": 124, "not_saved": 24, "total": 148, "percent_saved": 83.8, "percent_not_saved": 16.2}}, {"date_processed": "2024-02-11T19:57:07.147394", "total": 286, "saved": 241, "not_saved": 45, "percent_saved": 84.3, "percent_not_saved": 15.7, "d1": {"saved": 66, "not_saved": 10, "total": 76, "percent_saved": 86.8, "percent_not_saved": 13.2}, "d2": {"saved": 51, "not_saved": 11, "total": 62, "percent_saved": 82.3, "percent_not_saved": 17.7}, "d3": {"saved": 124, "not_saved": 24, "total": 148, "percent_saved": 83.8, "percent_not_saved": 16.2}}, {"date_processed": "2024-02-11T20:00:07.174970", "total": 286, "saved": 242, "not_saved": 44, "percent_saved": 84.6, "percent_not_saved": 15.4, "d1": {"saved": 66, "not_saved": 10, "total": 76, "percent_saved": 86.8, "percent_not_saved": 13.2}, "d2": {"saved": 52, "not_saved": 10, "total": 62, "percent_saved": 83.9, "percent_not_saved": 16.1}, "d3": {"saved": 124, "not_saved": 24, "total": 148, "percent_saved": 83.8, "percent_not_saved": 16.2}}, {"date_processed": "2024-02-11T20:02:47.010219", "total": 286, "saved": 258, "not_saved": 28, "percent_saved": 90.2, "percent_not_saved": 9.8, "d1": {"saved": 66, "not_saved": 10, "total": 76, "percent_saved": 86.8, "percent_not_saved": 13.2}, "d2": {"saved": 57, "not_saved": 5, "total": 62, "percent_saved": 91.9, "percent_not_saved": 8.1}, "d3": {"saved": 135, "not_saved": 13, "total": 148, "percent_saved": 91.2, "percent_not_saved": 8.8}}]