[{"location": "Ephrata, PA (War Memorial Field)", "date": "2024-02-17T11:00:00", "at_home": true, "opponent": "Franklin and Marshall College"}, {"location": "Ephrata, PA (War Memorial Field)", "date": "2024-02-17T14:00:00", "at_home": true, "opponent": "Franklin and Marshall College"}, {"location": "Ephrata, PA (War Memorial Field)", "date": "2024-02-18T11:00:00", "at_home": true, "opponent": "Penn State Harrisburg"}, {"location": "Ephrata, PA (War Memorial Field)", "date": "2024-02-18T14:00:00", "at_home": true, "opponent": "Penn State Harrisburg"}, {"location": "Clinton, NY", "date": "2024-03-02T13:30:00", "at_home": false, "opponent": "Clarkson University"}, {"location": "Clinton, NY", "date": "2024-03-03T11:00:00", "at_home": false, "opponent": "Clarkson University"}, {"location": "Clinton, NY", "date": "2024-03-03T13:00:00", "at_home": false, "opponent": "Clarkson University"}, {"location": "Ithaca, NY", "date": "2024-03-22T15:00:00", "at_home": false, "opponent": "Clarkson University"}, {"location": "Ithaca, NY", "date": "2024-03-23T15:00:00", "at_home": false, "opponent": "Clarkson University"}, {"location": "Ithaca, NY", "date": "2024-03-23T12:00:00", "at_home": false, "opponent": "Clarkson University"}, {"location": "Cortland, NY", "date": "2024-03-26T15:00:00", "at_home": false, "opponent": "Clarkson University"}, {"location": "Rochester, NY", "date": "2024-03-29T15:00:00", "at_home": false, "opponent": "Clarkson University"}, {"location": "Rochester, NY", "date": "2024-03-30T15:00:00", "at_home": false, "opponent": "Clarkson University"}, {"location": "Rochester, NY", "date": "2024-03-30T12:00:00", "at_home": false, "opponent": "Clarkson University"}, {"location": "Jack Phillips Stadium at Snell Field", "date": "2024-04-02T15:00:00", "at_home": true, "opponent": "Plattsburgh State"}, {"location": "Plattsburgh, NY", "date": "2024-04-10T16:00:00", "at_home": false, "opponent": "Clarkson University"}, {"location": "Jack Phillips Stadium at Snell Field", "date": "2024-04-05T16:00:00", "at_home": true, "opponent": "University of Rochester"}, {"location": "Jack Phillips Stadium at Snell Field", "date": "2024-04-06T15:00:00", "at_home": true, "opponent": "University of Rochester"}, {"location": "Jack Phillips Stadium at Snell Field", "date": "2024-04-06T12:00:00", "at_home": true, "opponent": "University of Rochester"}, {"location": "Jack Phillips Stadium at Snell Field", "date": "2024-04-13T12:00:00", "at_home": true, "opponent": "Union College"}, {"location": "Jack Phillips Stadium at Snell Field", "date": "2024-04-13T14:00:00", "at_home": true, "opponent": "Union College"}, {"location": "Jack Phillips Stadium at Snell Field", "date": "2024-04-14T12:00:00", "at_home": true, "opponent": "Skidmore College"}, {"location": "Jack Phillips Stadium at Snell Field", "date": "2024-04-14T14:00:00", "at_home": true, "opponent": "Skidmore College"}, {"location": "Jack Phillips Stadium at Snell Field", "date": "2024-04-17T16:00:00", "at_home": true, "opponent": "SUNY Canton"}, {"location": "Jack Phillips Stadium at Snell Field", "date": "2024-04-19T15:00:00", "at_home": true, "opponent": "Hobart College"}, {"location": "Jack Phillips Stadium at Snell Field", "date": "2024-04-20T12:00:00", "at_home": true, "opponent": "Hobart College"}, {"location": "Jack Phillips Stadium at Snell Field", "date": "2024-04-20T14:00:00", "at_home": true, "opponent": "Hobart College"}, {"location": "Jack Phillips Stadium at Snell Field", "date": "2024-04-23T14:00:00", "at_home": true, "opponent": "Oswego State"}, {"location": "Jack Phillips Stadium at Snell Field", "date": "2024-04-23T16:00:00", "at_home": true, "opponent": "Oswego State"}, {"location": "Canton, NY", "date": "2024-04-27T12:00:00", "at_home": false, "opponent": "Clarkson University"}, {"location": "Canton, NY", "date": "2024-04-27T14:00:00", "at_home": false, "opponent": "Clarkson University"}, {"location": "Jack Phillips Stadium at Snell Field", "date": "2024-04-26T15:00:00", "at_home": true, "opponent": "St. Lawrence University"}, {"location": "", "date": "2024-03-15T00:00:00", "at_home": true, "opponent": "Oneonta"}, {"location": "Davenport, FL (Northeast Regional Park)", "date": "2024-03-16T12:45:00", "at_home": true, "opponent": "UMass Dartmouth"}, {"location": "Davenport, FL (Northeast Regional Park)", "date": "2024-03-16T15:00:00", "at_home": true, "opponent": "UMass Dartmouth"}, {"location": "Davenport, FL (Northeast Regional Park)", "date": "2024-03-17T09:15:00", "at_home": true, "opponent": "University of Wisconsin-Eau Claire"}, {"location": "Davenport, FL (Northeast Regional Park)", "date": "2024-03-17T11:30:00", "at_home": true, "opponent": "University of Wisconsin-Eau Claire"}, {"location": "Davenport, FL (Northeast Regional Park)", "date": "2024-03-19T16:30:00", "at_home": true, "opponent": "Lawrence University"}, {"location": "Auburndale, FL (Lake Myrtle Field 7)", "date": "2024-03-20T12:00:00", "at_home": true, "opponent": "Framingham State University"}]