[{"location": "Salisbury, Md.", "date": "2024-02-16T14:00:00", "at_home": false, "opponent": "SUNY Cortland"}, {"location": "Salisbury, Md.", "date": "2024-02-17T10:00:00", "at_home": true, "opponent": "Widener"}, {"location": "Salisbury, Md.", "date": "2024-02-18T12:00:00", "at_home": false, "opponent": "SUNY Cortland"}, {"location": "Greensboro, N.C.", "date": "2024-02-22T15:30:00", "at_home": true, "opponent": "Marietta"}, {"location": "Greensboro, N.C.", "date": "2024-02-23T20:00:00", "at_home": true, "opponent": "Lynchburg"}, {"location": "Greensboro, N.C.", "date": "2024-02-24T11:00:00", "at_home": true, "opponent": "Christopher Newport"}, {"location": "Greensboro, N.C.", "date": "2024-02-25T11:00:00", "at_home": true, "opponent": "Denison"}, {"location": "Union, N.J.", "date": "2024-03-01T15:00:00", "at_home": false, "opponent": "SUNY Cortland"}, {"location": "Union, N.J.", "date": "2024-03-02T12:00:00", "at_home": false, "opponent": "SUNY Cortland"}, {"location": "Thousand Oaks, Calif.", "date": "2024-03-08T15:00:00", "at_home": false, "opponent": "SUNY Cortland"}, {"location": "Thousand Oaks, Calif.", "date": "2024-03-09T15:00:00", "at_home": false, "opponent": "SUNY Cortland"}, {"location": "Thousand Oaks, Calif.", "date": "2024-03-10T15:00:00", "at_home": false, "opponent": "SUNY Cortland"}, {"location": "La Verne, Calif.", "date": "2024-03-12T15:00:00", "at_home": false, "opponent": "SUNY Cortland"}, {"location": "Orange, Calif.", "date": "2024-03-14T19:00:00", "at_home": false, "opponent": "SUNY Cortland"}, {"location": "Orange, Calif.", "date": "2024-03-15T15:00:00", "at_home": false, "opponent": "SUNY Cortland"}, {"location": "Orange, Calif.", "date": "2024-03-16T13:00:00", "at_home": false, "opponent": "SUNY Cortland"}, {"location": "Oneonta, N.Y.", "date": "2024-03-22T15:00:00", "at_home": false, "opponent": "SUNY Cortland"}, {"location": "Oneonta, N.Y.", "date": "2024-03-23T12:00:00", "at_home": false, "opponent": "SUNY Cortland"}, {"location": "Oneonta, N.Y.", "date": "2024-03-23T15:00:00", "at_home": false, "opponent": "SUNY Cortland"}, {"location": "Robert H. Wallace '53 Field", "date": "2024-03-26T15:00:00", "at_home": true, "opponent": "Clarkson"}, {"location": "Robert H. Wallace '53 Field", "date": "2024-03-29T15:00:00", "at_home": true, "opponent": "Plattsburgh"}, {"location": "Robert H. Wallace '53 Field", "date": "2024-03-30T12:00:00", "at_home": true, "opponent": "Plattsburgh (Game 1)"}, {"location": "Robert H. Wallace '53 Field", "date": "2024-03-30T15:00:00", "at_home": true, "opponent": "Plattsburgh (Game 2)"}, {"location": "Robert H. Wallace '53 Field", "date": "2024-04-02T15:00:00", "at_home": true, "opponent": "RIT"}, {"location": "Robert H. Wallace '53 Field", "date": "2024-04-05T15:00:00", "at_home": true, "opponent": "Brockport"}, {"location": "Robert H. Wallace '53 Field", "date": "2024-04-06T12:00:00", "at_home": true, "opponent": "Brockport (Game 1)"}, {"location": "Robert H. Wallace '53 Field", "date": "2024-04-06T15:00:00", "at_home": true, "opponent": "Brockport (Game 2)"}, {"location": "Rochester, N.Y.", "date": "2024-04-10T18:00:00", "at_home": false, "opponent": "SUNY Cortland"}, {"location": "Robert H. Wallace '53 Field", "date": "2024-04-11T14:30:00", "at_home": true, "opponent": "Castleton"}, {"location": "Rochester, N.Y.", "date": "2024-04-16T15:00:00", "at_home": false, "opponent": "SUNY Cortland"}, {"location": "Oswego, N.Y.", "date": "2024-04-19T15:00:00", "at_home": false, "opponent": "SUNY Cortland"}, {"location": "Oswego, N.Y.", "date": "2024-04-20T12:00:00", "at_home": false, "opponent": "SUNY Cortland"}, {"location": "Oswego, N.Y.", "date": "2024-04-20T15:00:00", "at_home": false, "opponent": "SUNY Cortland"}, {"location": "Robert H. Wallace '53 Field", "date": "2024-04-24T16:00:00", "at_home": true, "opponent": "St. Lawrence"}, {"location": "New Paltz, N.Y.", "date": "2024-04-26T15:00:00", "at_home": false, "opponent": "SUNY Cortland"}, {"location": "New Paltz, N.Y.", "date": "2024-04-27T12:00:00", "at_home": false, "opponent": "SUNY Cortland"}, {"location": "New Paltz, N.Y.", "date": "2024-04-27T15:00:00", "at_home": false, "opponent": "SUNY Cortland"}, {"location": "Robert H. Wallace '53 Field", "date": "2024-04-30T15:30:00", "at_home": true, "opponent": "Alfred State"}, {"location": "Robert H. Wallace '53 Field", "date": "2024-05-03T15:00:00", "at_home": true, "opponent": "Fredonia"}, {"location": "Robert H. Wallace '53 Field", "date": "2024-05-04T12:00:00", "at_home": true, "opponent": "Fredonia (Game 1)"}, {"location": "Robert H. Wallace '53 Field", "date": "2024-05-04T15:00:00", "at_home": true, "opponent": "Fredonia (Game 2)"}, {"location": "TBA", "date": "2024-05-09T00:00:00", "at_home": false, "opponent": "SUNY Cortland"}, {"location": "TBA", "date": "2024-05-10T00:00:00", "at_home": false, "opponent": "SUNY Cortland"}, {"location": "TBA", "date": "2024-05-11T00:00:00", "at_home": false, "opponent": "SUNY Cortland"}, {"location": "TBA", "date": "2024-05-17T00:00:00", "at_home": false, "opponent": "SUNY Cortland"}, {"location": "TBA", "date": "2024-05-18T00:00:00", "at_home": false, "opponent": "SUNY Cortland"}, {"location": "TBA", "date": "2024-05-19T00:00:00", "at_home": false, "opponent": "SUNY Cortland"}, {"location": "TBA", "date": "2024-05-24T00:00:00", "at_home": false, "opponent": "SUNY Cortland"}, {"location": "TBA", "date": "2024-05-25T00:00:00", "at_home": false, "opponent": "SUNY Cortland"}, {"location": "Eastlake, Ohio", "date": "2024-05-31T00:00:00", "at_home": false, "opponent": "SUNY Cortland"}, {"location": "Robert H. Wallace '53 Field", "date": "2024-04-13T13:00:00", "at_home": true, "opponent": "Penn State Berks (Game 1)"}, {"location": "Robert H. Wallace '53 Field", "date": "2024-04-13T16:00:00", "at_home": true, "opponent": "Penn State Berks (Game 2)"}]